<server description="new server">

	<!-- Enable features -->
	<featureManager>
        <feature>cdi-1.2</feature>
        <feature>ejb-3.2</feature>
        <feature>ejbPersistentTimer-3.2</feature>
        <feature>jaxb-2.2</feature>
        <feature>jaxrs-2.0</feature>
        <feature>jaxws-2.2</feature>
        <feature>jms-2.0</feature>
        <feature>jndi-1.0</feature>
        <feature>localConnector-1.0</feature>
        <feature>servlet-3.1</feature>
    <!--    <feature>wmqJmsClient-2.0</feature>  -->
    </featureManager>

	<!-- This template enables security. To get the full use of all the capabilities, 
		a keystore and user registry are required. -->

	<!-- For the keystore, default keys are generated and stored in a keystore. 
		To provide the keystore password, generate an encoded password using bin/securityUtility 
		encode and add it below in the password attribute of the keyStore element. 
		Then uncomment the keyStore element. -->
	<!-- <keyStore password=""/> --> 

	<!--For a user registry configuration, configure your user registry. For 
		example, configure a basic user registry using the basicRegistry element. 
		Specify your own user name below in the name attribute of the user element. 
		For the password, generate an encoded password using bin/securityUtility 
		encode and add it in the password attribute of the user element. Then uncomment 
		the user element. -->
	<basicRegistry id="basic" realm="BasicRealm">
		<user name="dvd" password="dvdpsw"/> 
	</basicRegistry>

	<keyStore id="defaultKeyStore" password="dvdpsw"/>
	
	<!-- 
	********	VARIABLES AND JNDIENTRY 	**********
	-->
	
	<jndiEntry jndiName="serverName" value="${wlp.server.name}"/>
	<jndiEntry jndiName="outputDir" value="${server.output.dir}"/>
	
	<!--
	 <variable name="wmqJmsClient.rar.location" value="${server.config.dir}/resources/jmsLib/wmq.jmsra-9.2.3.0.rar"/>
	-->
	<!-- 
	********	SHARED LIB AND PROPERTIES 	**********
	-->
    
    
    
    <library id="WFMResource">
	    <fileset dir="${server.config.dir}/resources/lib" includes="*.jar" scanInterval="5s"/>
    </library> 
    <!--
    <library id="OracleLib">
    	<fileset dir="${server.config.dir}/resources/oraclejdbc" includes="*.jar" scanInterval="5s"/>
    </library>
    -->
	 <library id="postgresql-library">
		<fileset
			dir="${server.config.dir}/resources/postgresLib/"
			id="PostgreSQLFileset"
			includes="postgresql-42.2.19.jar" />
	</library>
	
    <library id="properties">
		<folder dir="${server.config.dir}/resources/properties/sviluppo"/>
    </library> 
    
   

	<!-- 
	********	DATABASE 	**********
	-->
	
	<!--<authData id="oracleUser" password="${DB_PASSWORD}" user="${DB_USER}"/>-->    
	
	<!-- DATASOURCE FOR WASTE APP -->
	<!--
	<dataSource enableConnectionCasting="true" id="WASTE" jdbcDriverRef="OracleJDBCDriver" jndiName="jdbc/WASTES" transactional="false">
    	<properties.oracle URL="jdbc:oracle:thin:@10.64.4.97:1521:dbjstbm" password="${DB_PASSWORD}" user="${DB_USER}"/>
    	<connectionManager connectionTimeout="180s" maxPoolSize="40" minPoolSize="1"/>
    </dataSource>
    <jdbcDriver id="OracleJDBCDriver" javax.sql.ConnectionPoolDataSource="oracle.jdbc.pool.OracleConnectionPoolDataSource" libraryRef="OracleLib">
    </jdbcDriver>-->
    
    <!-- DATASOURCE FOR PERSISTENT TIMER -->
	<!--
    <dataSource id="DefaultDataSource" jdbcDriverRef="OracleJDBCDriver" transactional="false">
    	<properties.oracle URL="jdbc:oracle:thin:@10.64.4.97:1521:dbjstbm" password="${DB_PASSWORD}" user="${DB_USER}"/>
    	<connectionManager connectionTimeout="180s" maxPoolSize="40" minPoolSize="1"/>
    </dataSource>
    <jdbcDriver id="OracleJDBCDriver" javax.sql.ConnectionPoolDataSource="oracle.jdbc.pool.OracleConnectionPoolDataSource" libraryRef="OracleLib">
    </jdbcDriver>-->
    
      <!-- The following enables failover for persistent timers -->
      <!-- <persistentExecutor id="defaultEJBPersistentTimerExecutor" missedTaskThreshold="5m"/>-->
   
   <!--
    <transaction clientInactivityTimeout="360s" heuristicRetryInterval="0" heuristicRetryWait="0" propogatedOrBMTTranLifetimeTimeout="2700s" recoverOnStartup="true" totalTranLifetimeTimeout="2700s"/>
     -->
  
  
   <!--
	***********   POSTGRES ********
	-->
  
    <!-- Definizione datasource DB INIZIO -->
	
	<dataSource id="WASTES" jndiName="jdbc/WASTES">
		<connectionManager maxPoolSize="100" minPoolSize="10" purgePolicy="FailingConnectionOnly"/>
		<jdbcDriver jdbcDriverRef="postgresql-driver" libraryRef="postgresql-library"/>
		<properties.postgresql currentSchema="WASTES" databaseName="${DB_NAME}" password="${DB_PASSWORD}" portNumber="${DB_SERVER_PORT}" serverName="${DB_SERVER_NAME}" user="${DB_USER}"/>
	</dataSource>
	
	<dataSource id="DefaultDataSource">
		<connectionManager maxPoolSize="100" minPoolSize="10" purgePolicy="FailingConnectionOnly"/>
		<jdbcDriver jdbcDriverRef="postgresql-driver" libraryRef="postgresql-library"/>
		<properties.postgresql currentSchema="WASTES" databaseName="${DB_NAME}" password="${DB_PASSWORD}" portNumber="${DB_SERVER_PORT}" serverName="${DB_SERVER_NAME}" user="${DB_USER}"/>
	</dataSource>
	
	<jdbcDriver id="postgresql-driver" javax.sql.ConnectionPoolDataSource="org.postgresql.ds.PGConnectionPoolDataSource" javax.sql.XADataSource="org.postgresql.xa.PGXADataSource" libraryRef="postgresql-library"/>
		
	
	<transaction clientInactivityTimeout="1800s" heuristicRetryInterval="0" heuristicRetryWait="0" propogatedOrBMTTranLifetimeTimeout="2700s" recoverOnStartup="true" totalTranLifetimeTimeout="2700s"/>
		
	<!-- Definizione datasource DB FINE --> 
  
  
  
  
    <!--
	***********   AMQ ********
	-->
	
	<!-- definizione Connection Factory AMQ -->
    
	<connectionManager
		id="myConnMgrMM"
		maxPoolSize="400"
		minPoolSize="10"
		connectionTimeout="180s"
		agedTimeout="0"
		reapTime="3m"
		purgePolicy="EntirePool"
		maxIdleTime="60m" />
	
	<resourceAdapter id="activemq"
		location="${server.config.dir}/resources/jmsLib/activemq-rar-5.16.3.rar">
		<properties.activemq
			serverUrl="${QM_PROTOCOL}://${QM_HOSTNAME}:${QM_PORT}"
			userName="${QM_USER}"
			password="${QM_PASSWORD}"/>
	</resourceAdapter>
	
	<jmsQueueConnectionFactory jndiName="jms/WASTES_QUEUE">
		<properties.activemq
			serverUrl="${QM_PROTOCOL}://${QM_HOSTNAME}:${QM_PORT}"
			userName="${QM_USER}"
			password="${QM_PASSWORD}"/>
	</jmsQueueConnectionFactory>
	
	<jmsTopicConnectionFactory jndiName="jms/WASTES_TOPIC">
		<properties.activemq
			serverUrl="${QM_PROTOCOL}://${QM_HOSTNAME}:${QM_PORT}"
			userName="${QM_USER}"
			password="${QM_PASSWORD}"/>
	</jmsTopicConnectionFactory>
    
    <!--  definizione code e topic AMQ -->
    
    
    <!--  QUEUE -->
  
    <!--
	<jmsQueue id="jms/CONF_ECOS_QOutput" jndiName="jms/CONF_ECOS_QOutput">
	    <properties.activemq
	     PhysicalName="CONF_ECOS_QOutput"/>
	</jmsQueue>
	<jmsActivationSpec id="jms/CONF_ECOS_Q_AS">
	    <properties.activemq 
    	    destination="jms/CONF_ECOS_QOutput"
			destinationType="javax.jms.Queue"
			maxSessions="10"/>
	</jmsActivationSpec>
    -->
    
    
    <!--  TOPICS -->
	
	<!--
	<jmsTopic id="jms/CONS_STATO" jndiName="jms/CONS_STATO">
	    <properties.activemq
	     PhysicalName="CONS/STATO"/>
	</jmsTopic>
	<jmsActivationSpec id="jms/CONS_STATO_AS">
	    <properties.activemq
	        destination="jms/CONS_STATO"
			destinationType="javax.jms.Topic"
			maxSessions="10"/>
	</jmsActivationSpec>
	-->
	
	
	<!--  definizione code e topic -->
    
    <!--  QUEUE -->
    
    <jmsQueue id="jms/WDO_QInput" jndiName="jms/WDO_QInput">
	    <properties.activemq PhysicalName="WDO_QInput"/>
	</jmsQueue>
	<jmsQueue id="jms/WDO_QOutput" jndiName="jms/WDO_QOutput">
	     <properties.activemq PhysicalName="WDO_QOutput"/>
	</jmsQueue>
	<jmsQueue id="jms/ANAGR_SDC_QInput" jndiName="jms/ANAGR_SDC_QInput">
	    <properties.activemq PhysicalName="ANAGR_SDC_QInput"/>
	</jmsQueue>
	<jmsQueue id="jms/ANAGR_SDC_QOutput" jndiName="jms/ANAGR_SDC_QOutput">
	    <properties.activemq PhysicalName="ANAGR_SDC_QOutput"/>
	</jmsQueue>
	<jmsQueue id="jms/ANAGR_UTENTI_QInput" jndiName="jms/ANAGR_UTENTI_QInput">
	    <properties.activemq PhysicalName="ANAGR_UTENTI_QInput"/>
	</jmsQueue>
	<jmsQueue id="jms/ANAGR_UTENTI_QOutput" jndiName="jms/ANAGR_UTENTI_QOutput">
	     <properties.activemq PhysicalName="ANAGR_UTENTI_QOutput"/>
	</jmsQueue>
	<jmsQueue id="jms/ANAGR_CDL_QInput" jndiName="jms/ANAGR_CDL_QInput">
	    <properties.activemq PhysicalName="ANAGR_CDL_QInput"/>
	</jmsQueue>
	<jmsQueue id="jms/ANAGR_CDL_QOutput" jndiName="jms/ANAGR_CDL_QOutput">
	     <properties.activemq PhysicalName="ANAGR_CDL_QOutput"/>
	</jmsQueue>
	<jmsQueue id="jms/NOT_QInput" jndiName="jms/NOT_QInput">
	     <properties.activemq PhysicalName="NOT_QInput"/>
	</jmsQueue>
	<jmsQueue id="jms/NOT_QOutput" jndiName="jms/NOT_QOutput">
	     <properties.activemq PhysicalName="NOT_QOutput"/>
	</jmsQueue>
	<jmsQueue id="jms/ANAGR_MEZZI_QInput" jndiName="jms/ANAGR_MEZZI_QInput">
	     <properties.activemq PhysicalName="ANAGR_MEZZI_QInput"/>
	</jmsQueue>
	<jmsQueue id="jms/ANAGR_MEZZI_QOutput" jndiName="jms/ANAGR_MEZZI_QOutput">
	     <properties.activemq PhysicalName="ANAGR_MEZZI_QOutput"/>
	</jmsQueue>
	<jmsQueue id="jms/PERCORSI_EFFETTIVI_QInput" jndiName="jms/PERCORSI_EFFETTIVI_QInput">
	     <properties.activemq PhysicalName="PERCORSI_EFFETTIVI_QInput"/>
	</jmsQueue>
	<jmsQueue id="jms/PERCORSI_EFFETTIVI_QOutput" jndiName="jms/PERCORSI_EFFETTIVI_QOutput">
	     <properties.activemq PhysicalName="PERCORSI_EFFETTIVI_QOutput"/>
	</jmsQueue>
	<jmsQueue id="jms/CONS_WDO_QInput" jndiName="jms/CONS_WDO_QInput">
	     <properties.activemq PhysicalName="CONS_WDO_QInput"/>
	</jmsQueue>
	<jmsQueue id="jms/CONS_WDO_QOutput" jndiName="jms/CONS_WDO_QOutput">
	     <properties.activemq PhysicalName="CONS_WDO_QOutput"/>
	</jmsQueue>
	<jmsQueue id="jms/SEGNALAZIONI_QInput" jndiName="jms/SEGNALAZIONI_QInput">
	     <properties.activemq PhysicalName="SEGNALAZIONI_QInput"/>
	</jmsQueue>
	<jmsQueue id="jms/SEGNALAZIONI_QOutput" jndiName="jms/SEGNALAZIONI_QOutput">
	     <properties.activemq PhysicalName="SEGNALAZIONI_QOutput"/>
	</jmsQueue>
	<jmsQueue id="jms/ANAGR_CDR_QInput" jndiName="jms/ANAGR_CDR_QInput">
	     <properties.activemq PhysicalName="ANAGR_CDR_QInput"/>
	</jmsQueue>
	<jmsQueue id="jms/ANAGR_CDR_QOutput" jndiName="jms/ANAGR_CDR_QOutput">
	     <properties.activemq PhysicalName="ANAGR_CDR_QOutput"/>
	</jmsQueue>
	<jmsQueue id="jms/ANAGR_WASTECONTAINER_QInput" jndiName="jms/ANAGR_WASTECONTAINER_QInput">
	     <properties.activemq PhysicalName="ANAGR_WASTECONTAINER_QInput"/>
	</jmsQueue>
	<jmsQueue id="jms/ANAGR_WASTECONTAINER_QOutput" jndiName="jms/ANAGR_WASTECONTAINER_QOutput">
	     <properties.activemq PhysicalName="ANAGR_WASTECONTAINER_QOutput"/>
	</jmsQueue>
	<jmsQueue id="jms/CHECKLIST_QInput" jndiName="jms/CHECKLIST_QInput">
	     <properties.activemq PhysicalName="CHECKLIST_QInput"/>
	</jmsQueue>
	<jmsQueue id="jms/CHECKLIST_QOutput" jndiName="jms/CHECKLIST_QOutput">
	     <properties.activemq PhysicalName="CHECKLIST_QOutput"/>
	</jmsQueue>
	<jmsQueue id="jms/ANAGR_PDR_QInput" jndiName="jms/ANAGR_PDR_QInput">
	     <properties.activemq PhysicalName="ANAGR_PDR_QInput"/>
	</jmsQueue>
	<jmsQueue id="jms/ANAGR_PDR_QOutput" jndiName="jms/ANAGR_PDR_QOutput">
	     <properties.activemq PhysicalName="ANAGR_PDR_QOutput"/>
	</jmsQueue>
	<jmsQueue id="jms/LOG_SAPMessages" jndiName="jms/LOG_SAPMessages">
	     <properties.activemq PhysicalName="LOG_SAPMessages"/>
	</jmsQueue>
	<jmsQueue id="jms/ANAGR_UTENTI_EXT_QInput" jndiName="jms/ANAGR_UTENTI_EXT_QInput">
	     <properties.activemq PhysicalName="ANAGR_UTENTI_EXT_QInput"/>
	</jmsQueue>
	<jmsQueue id="jms/TCP_ANAGR_SDC_QInput" jndiName="jms/TCP_ANAGR_SDC_QInput">
	     <properties.activemq PhysicalName="TCP_ANAGR_SDC_QInput"/>
	</jmsQueue>
	<jmsQueue id="jms/TCP_ANAGR_SDC_QOutput" jndiName="jms/TCP_ANAGR_SDC_QOutput">
	     <properties.activemq PhysicalName="TCP_ANAGR_SDC_QOutput"/>
	</jmsQueue>
	<jmsQueue id="jms/TCP_BLACKLIST_QInput" jndiName="jms/TCP_BLACKLIST_QInput">
	     <properties.activemq PhysicalName="TCP_BLACKLIST_QInput"/>
	</jmsQueue>
	<jmsQueue id="jms/TCP_BLACKLIST_QOutput" jndiName="jms/TCP_BLACKLIST_QOutput">
	     <properties.activemq PhysicalName="TCP_BLACKLIST_QOutput"/>
	</jmsQueue>
	<jmsQueue id="jms/TCP_CONF_QOutput" jndiName="jms/TCP_CONF_QOutput">
	     <properties.activemq PhysicalName="TCP_CONF_QOutput"/>
	</jmsQueue>
	<jmsQueue id="jms/TCP_CONF_QInput" jndiName="jms/TCP_CONF_QInput">
	     <properties.activemq PhysicalName="TCP_CONF_QInput"/>
	</jmsQueue>
	<jmsQueue id="jms/TCP_AGG_SDC_QOutput" jndiName="jms/TCP_AGG_SDC_QOutput">
	     <properties.activemq PhysicalName="TCP_AGG_SDC_QOutput"/>
	</jmsQueue>
	<jmsQueue id="jms/TCP_AGG_SDC_QInput" jndiName="jms/TCP_AGG_SDC_QInput">
	     <properties.activemq PhysicalName="TCP_AGG_SDC_QInput"/>
	</jmsQueue>
	<jmsQueue id="jms/TCP_BLACKLIST_INIBITA_QOutput" jndiName="jms/TCP_BLACKLIST_INIBITA_QOutput">
	     <properties.activemq PhysicalName="TCP_BLACKLIST_INIBITA_QOutput"/>
	</jmsQueue>
	<jmsQueue id="jms/TCP_BLACKLIST_INIBITA_QInput" jndiName="jms/TCP_BLACKLIST_INIBITA_QInput">
	     <properties.activemq PhysicalName="TCP_BLACKLIST_INIBITA_QInput"/>
	</jmsQueue>
	<jmsQueue id="jms/ANAGR_BP_QInput" jndiName="jms/ANAGR_BP_QInput">
	     <properties.activemq PhysicalName="ANAGR_BP_QInput"/>
	</jmsQueue>
	<jmsQueue id="jms/ANAGR_BP_QOutput" jndiName="jms/ANAGR_BP_QOutput">
	     <properties.activemq PhysicalName="ANAGR_BP_QOutput"/>
	</jmsQueue>
	<jmsQueue id="jms/ANAGR_CONTRATTI_QOutput" jndiName="jms/ANAGR_CONTRATTI_QOutput">
	     <properties.activemq PhysicalName="ANAGR_CONTRATTI_QOutput"/>
	</jmsQueue>
	<jmsQueue id="jms/ANAGR_CONTRATTI_QInput" jndiName="jms/ANAGR_CONTRATTI_QInput">
	     <properties.activemq PhysicalName="ANAGR_CONTRATTI_QInput"/>
	</jmsQueue>
	<jmsQueue id="jms/ALTARES_STAMPINGS_QInput" jndiName="jms/ALTARES_STAMPINGS_QInput">
	     <properties.activemq PhysicalName="ALTARES_STAMPINGS_QInput"/>
	</jmsQueue>
	<jmsQueue id="jms/WFM_CONF_QInput" jndiName="jms/WFM_CONF_QInput">
	     <properties.activemq PhysicalName="WFM_CONF_QInput"/>
	</jmsQueue>
	<jmsQueue id="jms/WFM_CONF_QOutput" jndiName="jms/WFM_CONF_QOutput">
	     <properties.activemq PhysicalName="WFM_CONF_QOutput"/>
	</jmsQueue>
	<jmsQueue id="jms/ANAGR_MEZZI_EXT_QInput" jndiName="jms/ANAGR_MEZZI_EXT_QInput">
	     <properties.activemq PhysicalName="ANAGR_MEZZI_EXT_QInput"/>
	</jmsQueue>
	<jmsQueue id="jms/ANAGR_MEZZI_EXT_QOutput" jndiName="jms/ANAGR_MEZZI_EXT_QOutput">
	     <properties.activemq PhysicalName="ANAGR_MEZZI_EXT_QOutput"/>
	</jmsQueue>
	<jmsQueue id="jms/ANAGR_CONTRATTI_PASSIVI_QInput" jndiName="jms/ANAGR_CONTRATTI_PASSIVI_QInput">
	     <properties.activemq PhysicalName="ANAGR_CONTRATTI_PASSIVI_QInput"/>
	</jmsQueue>
	<jmsQueue id="jms/ANAGR_CONTRATTI_PASSIVI_QOutput" jndiName="jms/ANAGR_CONTRATTI_PASSIVI_QOutput">
	     <properties.activemq PhysicalName="ANAGR_CONTRATTI_PASSIVI_QOutput"/>
	</jmsQueue>
	<jmsQueue id="jms/TCP_CONF_ISOLE_QOutput" jndiName="jms/TCP_CONF_ISOLE_QOutput">
	     <properties.activemq PhysicalName="TCP_CONF_ISOLE_QOutput"/>
	</jmsQueue>
	<jmsQueue id="jms/GIS_ITINERARI_NOTE_QInput" jndiName="jms/GIS_ITINERARI_NOTE_QInput">
	     <properties.activemq PhysicalName="GIS_ITINERARI_NOTE_QInput"/>
	</jmsQueue>
	<jmsQueue id="jms/CONF_ECOS_QInput" jndiName="jms/CONF_ECOS_QInput">
	     <properties.activemq PhysicalName="CONF_ECOS_QInput"/>
	</jmsQueue>
	<jmsQueue id="jms/CONF_ECOS_QOutput" jndiName="jms/CONF_ECOS_QOutput">
	     <properties.activemq PhysicalName="CONF_ECOS_QOutput"/>
	</jmsQueue> 
	
	<!--  TOPICS -->
	 
	<jmsTopic id="jms/CONS_STATO" jndiName="jms/CONS_STATO">
	    <properties.activemq PhysicalName="CONS/STATO"/>
	</jmsTopic>
	<jmsTopic id="jms/CONS_ODL" jndiName="jms/CONS_ODL">
	     <properties.activemq PhysicalName="CONS/ODL"/>
	</jmsTopic>
	<jmsTopic id="jms/CONS_SEG" jndiName="jms/CONS_SEG">
	     <properties.activemq PhysicalName="CONS/SEG"/>
	</jmsTopic>
	<jmsTopic id="jms/CONS_TRACKING" jndiName="jms/CONS_TRACKING">
	     <properties.activemq PhysicalName="CONS/TRACKING"/>
	</jmsTopic>
	<jmsTopic id="jms/CONS_CHECKLIST" jndiName="jms/CONS_CHECKLIST">
	     <properties.activemq PhysicalName="CONS/CHECKLIST"/>
	</jmsTopic>
	<jmsTopic id="jms/CONS_PESATA" jndiName="jms/CONS_PESATA">
	     <properties.activemq PhysicalName="CONS/PESATA"/>
	</jmsTopic>
	<jmsTopic id="jms/CONS_ANOM" jndiName="jms/CONS_ANOM">
	     <properties.activemq PhysicalName="CONS/ANOM"/>
	</jmsTopic>
	<jmsTopic id="jms/CONS_CONFERIMENTI" jndiName="jms/CONS_CONFERIMENTI">
	     <properties.activemq PhysicalName="CONS/CONFERIMENTI"/>
	</jmsTopic>
	<jmsTopic id="jms/CONS_DOTAZIONI" jndiName="jms/CONS_DOTAZIONI">
	     <properties.activemq PhysicalName="CONS/DOTAZIONI"/>
	</jmsTopic>
	<jmsTopic id="jms/CONS_ECOSTATION" jndiName="jms/CONS_ECOSTATION">
	     <properties.activemq PhysicalName="CONS/ECOSTATION"/>
	</jmsTopic>   
	

    <!--  definizione activation spec -->
    
    <!-- QUEUE AS-->
   
    <jmsActivationSpec id="jms/ANAGR_SDC_Q_AS">
	    <properties.activemq destination="jms/ANAGR_SDC_QInput" destinationType="javax.jms.Queue" maxSessions="10"/>
	</jmsActivationSpec>
	<jmsActivationSpec id="jms/ANAGR_UTENTI_Q_AS">
	    <properties.activemq destination="jms/ANAGR_UTENTI_QInput" destinationType="javax.jms.Queue" maxSessions="10"/>
	</jmsActivationSpec>
	<jmsActivationSpec id="jms/ANAGR_CDL_Q_AS">
	    <properties.activemq destination="jms/ANAGR_CDL_QInput" destinationType="javax.jms.Queue" maxSessions="10"/>
	</jmsActivationSpec>
	<jmsActivationSpec id="jms/WDO_Q_AS">
	    <properties.activemq destination="jms/WDO_QInput" destinationType="javax.jms.Queue" maxSessions="10"/>
	</jmsActivationSpec>
	<jmsActivationSpec id="jms/ANAGR_MEZZI_Q_AS">
	    <properties.activemq destination="jms/ANAGR_MEZZI_QInput" destinationType="javax.jms.Queue" maxSessions="10"/>
	</jmsActivationSpec>
	<jmsActivationSpec id="jms/NOT_Q_AS">
	    <properties.activemq destination="jms/NOT_QInput" destinationType="javax.jms.Queue" maxSessions="10"/>
	</jmsActivationSpec>
	<jmsActivationSpec id="jms/CONS_WDO_Q_AS">
	    <properties.activemq destination="jms/CONS_WDO_QOutput" destinationType="javax.jms.Queue" maxSessions="10"/>
	</jmsActivationSpec>
	<jmsActivationSpec id="jms/SEGNALAZIONI_Q_AS">
	    <properties.activemq destination="jms/SEGNALAZIONI_QOutput" destinationType="javax.jms.Queue" maxSessions="10"/>
	</jmsActivationSpec>
	<jmsActivationSpec id="jms/ANAGR_CDR_Q_AS">
	    <properties.activemq destination="jms/ANAGR_CDR_QInput" destinationType="javax.jms.Queue" maxSessions="10"/>
	</jmsActivationSpec>
	<jmsActivationSpec id="jms/ANAGR_WASTECONTAINER_Q_AS">
	    <properties.activemq destination="jms/ANAGR_WASTECONTAINER_QInput" destinationType="javax.jms.Queue" maxSessions="10"/>
	</jmsActivationSpec>
	<jmsActivationSpec id="jms/ANAGR_PDR_Q_AS">
	    <properties.activemq destination="jms/ANAGR_PDR_QInput" destinationType="javax.jms.Queue" maxSessions="10"/>
	</jmsActivationSpec>
	<jmsActivationSpec id="jms/CHECKLIST_Q_AS">
	    <properties.activemq destination="jms/CHECKLIST_QOutput" destinationType="javax.jms.Queue" maxSessions="10"/>
	</jmsActivationSpec>
	<jmsActivationSpec id="jms/LOG_SAPMessages_Q_AS">
	    <properties.activemq destination="jms/LOG_SAPMessages" destinationType="javax.jms.Queue" maxSessions="10"/>
	</jmsActivationSpec>
	<jmsActivationSpec id="jms/PERCORSI_EFFETTIVI_Q_AS">
	    <properties.activemq destination="jms/PERCORSI_EFFETTIVI_QOutput" destinationType="javax.jms.Queue" maxSessions="10"/>
	</jmsActivationSpec>
	<jmsActivationSpec id="jms/TCP_ANAGR_SDC_Q_AS">
	    <properties.activemq destination="jms/TCP_ANAGR_SDC_QInput" destinationType="javax.jms.Queue" maxSessions="10"/>
	</jmsActivationSpec>
	<jmsActivationSpec id="jms/TCP_BLACKLIST_Q_AS">
	    <properties.activemq destination="jms/TCP_BLACKLIST_QInput" destinationType="javax.jms.Queue" maxSessions="10"/>
	</jmsActivationSpec>
	<jmsActivationSpec id="jms/TCP_CONF_Q_AS">
	    <properties.activemq destination="jms/TCP_CONF_QOutput" destinationType="javax.jms.Queue" maxSessions="10"/>
	</jmsActivationSpec>
	<jmsActivationSpec id="jms/TCP_AGG_SDC_Q_AS">
	    <properties.activemq destination="jms/TCP_AGG_SDC_QOutput" destinationType="javax.jms.Queue" maxSessions="10"/>
	</jmsActivationSpec>
	<jmsActivationSpec id="jms/TCP_BLACKLIST_INIBITA_Q_AS">
	    <properties.activemq destination="jms/TCP_BLACKLIST_INIBITA_QOutput" destinationType="javax.jms.Queue" maxSessions="10"/>
	</jmsActivationSpec>
	<jmsActivationSpec id="jms/ANAGR_BP_Q_AS">
	    <properties.activemq destination="jms/ANAGR_BP_QInput" destinationType="javax.jms.Queue" maxSessions="10"/>
	</jmsActivationSpec>
	<jmsActivationSpec id="jms/ANAGR_CONTRATTI_Q_AS">
	    <properties.activemq destination="jms/ANAGR_CONTRATTI_QInput" destinationType="javax.jms.Queue" maxSessions="10"/>
	</jmsActivationSpec>
	<jmsActivationSpec id="jms/ALTARES_STAMPINGS_Q_AS">
	    <properties.activemq destination="jms/ALTARES_STAMPINGS_QInput" destinationType="javax.jms.Queue" maxSessions="10"/>
	</jmsActivationSpec>
	<jmsActivationSpec id="jms/WFM_CONF_Q_AS">
	    <properties.activemq destination="jms/WFM_CONF_QInput" destinationType="javax.jms.Queue" maxSessions="10"/>
	</jmsActivationSpec>
	<jmsActivationSpec id="jms/ANAGR_CONTRATTI_PASSIVI_Q_AS">
	    <properties.activemq destination="jms/ANAGR_CONTRATTI_PASSIVI_QInput" destinationType="javax.jms.Queue" maxSessions="10"/>
	</jmsActivationSpec>
	<jmsActivationSpec id="jms/TCP_CONF_ISOLE_Q_AS">
	    <properties.activemq destination="jms/TCP_CONF_ISOLE_QOutput" destinationType="javax.jms.Queue" maxSessions="10"/>
	</jmsActivationSpec>
	<jmsActivationSpec id="jms/GIS_ITINERARI_NOTE_Q_AS">
	    <properties.activemq destination="jms/GIS_ITINERARI_NOTE_QInput" destinationType="javax.jms.Queue" maxSessions="10"/>
	</jmsActivationSpec>
	<jmsActivationSpec id="jms/CONF_ECOS_Q_AS">
	    <properties.activemq destination="jms/CONF_ECOS_QOutput" destinationType="javax.jms.Queue" maxSessions="10"/>
	</jmsActivationSpec>  
	
	<!-- TOPIC AS-->
	  
	<jmsActivationSpec id="jms/CONS_STATO_AS">
	    <properties.activemq destination="jms/CONS_STATO"  destinationType="javax.jms.Topic" maxSessions="10"/>
	</jmsActivationSpec>
	<jmsActivationSpec id="jms/CONS_ODL_AS">
	    <properties.activemq destination="jms/CONS_ODL"  destinationType="javax.jms.Topic" maxSessions="10"/>
	</jmsActivationSpec>
	<jmsActivationSpec id="jms/CONS_SEG_AS">
	    <properties.activemq destination="jms/CONS_SEG"  destinationType="javax.jms.Topic" maxSessions="10"/>
	</jmsActivationSpec>
	<jmsActivationSpec id="jms/CONS_TRACKING_AS">
	    <properties.activemq destination="jms/CONS_TRACKING"  destinationType="javax.jms.Topic" maxSessions="10"/>
	</jmsActivationSpec>
	<jmsActivationSpec id="jms/CONS_CHECKLIST_AS">
	    <properties.activemq destination="jms/CONS_CHECKLIST"  destinationType="javax.jms.Topic" maxSessions="10"/>
	</jmsActivationSpec>
	<jmsActivationSpec id="jms/CONS_PESATA_AS">
	    <properties.activemq destination="jms/CONS_PESATA"  destinationType="javax.jms.Topic" maxSessions="10"/>
	</jmsActivationSpec>
	<jmsActivationSpec id="jms/CONS_ANOM_AS">
	    <properties.activemq destination="jms/CONS_ANOM"  destinationType="javax.jms.Topic" maxSessions="10"/>
	</jmsActivationSpec>
	<jmsActivationSpec id="jms/CONS_CONFERIMENTI_AS">
	    <properties.activemq destination="jms/CONS_CONFERIMENTI"  destinationType="javax.jms.Topic" maxSessions="10"/>
	</jmsActivationSpec>
	<jmsActivationSpec id="jms/CONS_ECOSTATION_AS">
	    <properties.activemq destination="jms/CONS_ECOSTATION"  destinationType="javax.jms.Topic" maxSessions="10"/>
	</jmsActivationSpec>
	<jmsActivationSpec id="jms/CONS_DOTAZIONI_AS">
	    <properties.activemq destination="jms/CONS_DOTAZIONI"  destinationType="javax.jms.Topic" maxSessions="10"/>
	</jmsActivationSpec>  
	
	
	<!--
	********** FINE AMQ *******
	-->
	

	<!-- 
	********	MQ 	**********
	-->
	
	<!-- connection factory >
	<authData id="auth1" password="2VGI5DNMvNVylRh1f4kw30Afwapqv5lsfo3AFeOdoPCg" user="mema"/-->
	
	<!-- MQ cloud UNLIMITED -->	
	
	<!-- 	
	<wasJmsEndpoint host="*" wasJmsPort="7277" wasJmsSSLPort="7279">
    </wasJmsEndpoint> -->


	
	<!--  definizione Connection Factory -->

    <!--
	<connectionManager agedTimeout="0" connectionTimeout="180s" id="ConMgr6" maxIdleTime="30m" maxPoolSize="30" minPoolSize="2" purgePolicy="EntirePool" reapTime="3m"/>
	-->
	
	<!-- CONNFACTORY FOR QUEUE -->
    <!--
	<jmsQueueConnectionFactory connectionManagerRef="ConMgr6" id="WFM_QUEUE_CF" jndiName="jms/WASTES_QUEUE">
   		<properties.wmqJms channel="${QM_CHANNEL}" hostName="${QM_HOSTNAME}" port="${QM_PORT}" queueManager="${QM_NAME}" transportType="CLIENT"/>
    </jmsQueueConnectionFactory>
	-->
	
	<!-- CONNFACTORY FOR TOPIC -->
	<!--
	<jmsTopicConnectionFactory connectionManagerRef="ConMgr6" id="WFM_TOPIC_CF" jndiName="jms/WASTES_TOPIC">
   		<properties.wmqJms channel="${QM_CHANNEL}" hostName="${QM_HOSTNAME}" port="${QM_PORT}" queueManager="${QM_NAME}" transportType="CLIENT"/>
    </jmsTopicConnectionFactory>
    -->
	
    <!--  definizione code e topic -->
    
    <!--  QUEUE -->
	
	<!--
    <jmsQueue id="jms/WDO_QInput" jndiName="jms/WDO_QInput">
	    <properties.wmqJms baseQueueManagerName="${QM_NAME}" baseQueueName="WDO_QInput"/>
	</jmsQueue>
	<jmsQueue id="jms/WDO_QOutput" jndiName="jms/WDO_QOutput">
	    <properties.wmqJms baseQueueManagerName="${QM_NAME}" baseQueueName="WDO_QOutput"/>
	</jmsQueue>
	<jmsQueue id="jms/ANAGR_SDC_QInput" jndiName="jms/ANAGR_SDC_QInput">
	    <properties.wmqJms baseQueueManagerName="${QM_NAME}" baseQueueName="ANAGR_SDC_QInput"/>
	</jmsQueue>
	<jmsQueue id="jms/ANAGR_SDC_QOutput" jndiName="jms/ANAGR_SDC_QOutput">
	    <properties.wmqJms baseQueueManagerName="${QM_NAME}" baseQueueName="ANAGR_SDC_QOutput"/>
	</jmsQueue>
	<jmsQueue id="jms/ANAGR_UTENTI_QInput" jndiName="jms/ANAGR_UTENTI_QInput">
	    <properties.wmqJms baseQueueManagerName="${QM_NAME}" baseQueueName="ANAGR_UTENTI_QInput"/>
	</jmsQueue>
	<jmsQueue id="jms/ANAGR_UTENTI_QOutput" jndiName="jms/ANAGR_UTENTI_QOutput">
	    <properties.wmqJms baseQueueManagerName="${QM_NAME}" baseQueueName="ANAGR_UTENTI_QOutput"/>
	</jmsQueue>
	<jmsQueue id="jms/ANAGR_CDL_QInput" jndiName="jms/ANAGR_CDL_QInput">
	    <properties.wmqJms baseQueueManagerName="${QM_NAME}" baseQueueName="ANAGR_CDL_QInput"/>
	</jmsQueue>
	<jmsQueue id="jms/ANAGR_CDL_QOutput" jndiName="jms/ANAGR_CDL_QOutput">
	    <properties.wmqJms baseQueueManagerName="${QM_NAME}" baseQueueName="ANAGR_CDL_QOutput"/>
	</jmsQueue>
	<jmsQueue id="jms/NOT_QInput" jndiName="jms/NOT_QInput">
	    <properties.wmqJms baseQueueManagerName="${QM_NAME}" baseQueueName="NOT_QInput"/>
	</jmsQueue>
	<jmsQueue id="jms/NOT_QOutput" jndiName="jms/NOT_QOutput">
	    <properties.wmqJms baseQueueManagerName="${QM_NAME}" baseQueueName="NOT_QOutput"/>
	</jmsQueue>
	<jmsQueue id="jms/ANAGR_MEZZI_QInput" jndiName="jms/ANAGR_MEZZI_QInput">
	    <properties.wmqJms baseQueueManagerName="${QM_NAME}" baseQueueName="ANAGR_MEZZI_QInput"/>
	</jmsQueue>
	<jmsQueue id="jms/ANAGR_MEZZI_QOutput" jndiName="jms/ANAGR_MEZZI_QOutput">
	    <properties.wmqJms baseQueueManagerName="${QM_NAME}" baseQueueName="ANAGR_MEZZI_QOutput"/>
	</jmsQueue>
	<jmsQueue id="jms/PERCORSI_EFFETTIVI_QInput" jndiName="jms/PERCORSI_EFFETTIVI_QInput">
	    <properties.wmqJms baseQueueManagerName="${QM_NAME}" baseQueueName="PERCORSI_EFFETTIVI_QInput"/>
	</jmsQueue>
	<jmsQueue id="jms/PERCORSI_EFFETTIVI_QOutput" jndiName="jms/PERCORSI_EFFETTIVI_QOutput">
	    <properties.wmqJms baseQueueManagerName="${QM_NAME}" baseQueueName="PERCORSI_EFFETTIVI_QOutput"/>
	</jmsQueue>
	<jmsQueue id="jms/CONS_WDO_QInput" jndiName="jms/CONS_WDO_QInput">
	    <properties.wmqJms baseQueueManagerName="${QM_NAME}" baseQueueName="CONS_WDO_QInput"/>
	</jmsQueue>
	<jmsQueue id="jms/CONS_WDO_QOutput" jndiName="jms/CONS_WDO_QOutput">
	    <properties.wmqJms baseQueueManagerName="${QM_NAME}" baseQueueName="CONS_WDO_QOutput"/>
	</jmsQueue>
	<jmsQueue id="jms/SEGNALAZIONI_QInput" jndiName="jms/SEGNALAZIONI_QInput">
	    <properties.wmqJms baseQueueManagerName="${QM_NAME}" baseQueueName="SEGNALAZIONI_QInput"/>
	</jmsQueue>
	<jmsQueue id="jms/SEGNALAZIONI_QOutput" jndiName="jms/SEGNALAZIONI_QOutput">
	    <properties.wmqJms baseQueueManagerName="${QM_NAME}" baseQueueName="SEGNALAZIONI_QOutput"/>
	</jmsQueue>
	<jmsQueue id="jms/ANAGR_CDR_QInput" jndiName="jms/ANAGR_CDR_QInput">
	    <properties.wmqJms baseQueueManagerName="${QM_NAME}" baseQueueName="ANAGR_CDR_QInput"/>
	</jmsQueue>
	<jmsQueue id="jms/ANAGR_CDR_QOutput" jndiName="jms/ANAGR_CDR_QOutput">
	    <properties.wmqJms baseQueueManagerName="${QM_NAME}" baseQueueName="ANAGR_CDR_QOutput"/>
	</jmsQueue>
	<jmsQueue id="jms/ANAGR_WASTECONTAINER_QInput" jndiName="jms/ANAGR_WASTECONTAINER_QInput">
	    <properties.wmqJms baseQueueManagerName="${QM_NAME}" baseQueueName="ANAGR_WASTECONTAINER_QInput"/>
	</jmsQueue>
	<jmsQueue id="jms/ANAGR_WASTECONTAINER_QOutput" jndiName="jms/ANAGR_WASTECONTAINER_QOutput">
	    <properties.wmqJms baseQueueManagerName="${QM_NAME}" baseQueueName="ANAGR_WASTECONTAINER_QOutput"/>
	</jmsQueue>
	<jmsQueue id="jms/CHECKLIST_QInput" jndiName="jms/CHECKLIST_QInput">
	    <properties.wmqJms baseQueueManagerName="${QM_NAME}" baseQueueName="CHECKLIST_QInput"/>
	</jmsQueue>
	<jmsQueue id="jms/CHECKLIST_QOutput" jndiName="jms/CHECKLIST_QOutput">
	    <properties.wmqJms baseQueueManagerName="${QM_NAME}" baseQueueName="CHECKLIST_QOutput"/>
	</jmsQueue>
	<jmsQueue id="jms/ANAGR_PDR_QInput" jndiName="jms/ANAGR_PDR_QInput">
	    <properties.wmqJms baseQueueManagerName="${QM_NAME}" baseQueueName="ANAGR_PDR_QInput"/>
	</jmsQueue>
	<jmsQueue id="jms/ANAGR_PDR_QOutput" jndiName="jms/ANAGR_PDR_QOutput">
	    <properties.wmqJms baseQueueManagerName="${QM_NAME}" baseQueueName="ANAGR_PDR_QOutput"/>
	</jmsQueue>
	<jmsQueue id="jms/LOG_SAPMessages" jndiName="jms/LOG_SAPMessages">
	    <properties.wmqJms baseQueueManagerName="${QM_NAME}" baseQueueName="LOG_SAPMessages"/>
	</jmsQueue>
	<jmsQueue id="jms/ANAGR_UTENTI_EXT_QInput" jndiName="jms/ANAGR_UTENTI_EXT_QInput">
	    <properties.wmqJms baseQueueManagerName="${QM_NAME}" baseQueueName="ANAGR_UTENTI_EXT_QInput"/>
	</jmsQueue>
	<jmsQueue id="jms/TCP_ANAGR_SDC_QInput" jndiName="jms/TCP_ANAGR_SDC_QInput">
	    <properties.wmqJms baseQueueManagerName="${QM_NAME}" baseQueueName="TCP_ANAGR_SDC_QInput"/>
	</jmsQueue>
	<jmsQueue id="jms/TCP_ANAGR_SDC_QOutput" jndiName="jms/TCP_ANAGR_SDC_QOutput">
	    <properties.wmqJms baseQueueManagerName="${QM_NAME}" baseQueueName="TCP_ANAGR_SDC_QOutput"/>
	</jmsQueue>
	<jmsQueue id="jms/TCP_BLACKLIST_QInput" jndiName="jms/TCP_BLACKLIST_QInput">
	    <properties.wmqJms baseQueueManagerName="${QM_NAME}" baseQueueName="TCP_BLACKLIST_QInput"/>
	</jmsQueue>
	<jmsQueue id="jms/TCP_BLACKLIST_QOutput" jndiName="jms/TCP_BLACKLIST_QOutput">
	    <properties.wmqJms baseQueueManagerName="${QM_NAME}" baseQueueName="TCP_BLACKLIST_QOutput"/>
	</jmsQueue>
	<jmsQueue id="jms/TCP_CONF_QOutput" jndiName="jms/TCP_CONF_QOutput">
	    <properties.wmqJms baseQueueManagerName="${QM_NAME}" baseQueueName="TCP_CONF_QOutput"/>
	</jmsQueue>
	<jmsQueue id="jms/TCP_CONF_QInput" jndiName="jms/TCP_CONF_QInput">
	    <properties.wmqJms baseQueueManagerName="${QM_NAME}" baseQueueName="TCP_CONF_QInput"/>
	</jmsQueue>
	<jmsQueue id="jms/TCP_AGG_SDC_QOutput" jndiName="jms/TCP_AGG_SDC_QOutput">
	    <properties.wmqJms baseQueueManagerName="${QM_NAME}" baseQueueName="TCP_AGG_SDC_QOutput"/>
	</jmsQueue>
	<jmsQueue id="jms/TCP_AGG_SDC_QInput" jndiName="jms/TCP_AGG_SDC_QInput">
	    <properties.wmqJms baseQueueManagerName="${QM_NAME}" baseQueueName="TCP_AGG_SDC_QInput"/>
	</jmsQueue>
	<jmsQueue id="jms/TCP_BLACKLIST_INIBITA_QOutput" jndiName="jms/TCP_BLACKLIST_INIBITA_QOutput">
	    <properties.wmqJms baseQueueManagerName="${QM_NAME}" baseQueueName="TCP_BLACKLIST_INIBITA_QOutput"/>
	</jmsQueue>
	<jmsQueue id="jms/TCP_BLACKLIST_INIBITA_QInput" jndiName="jms/TCP_BLACKLIST_INIBITA_QInput">
	    <properties.wmqJms baseQueueManagerName="${QM_NAME}" baseQueueName="TCP_BLACKLIST_INIBITA_QInput"/>
	</jmsQueue>
	<jmsQueue id="jms/ANAGR_BP_QInput" jndiName="jms/ANAGR_BP_QInput">
	    <properties.wmqJms baseQueueManagerName="${QM_NAME}" baseQueueName="ANAGR_BP_QInput"/>
	</jmsQueue>
	<jmsQueue id="jms/ANAGR_BP_QOutput" jndiName="jms/ANAGR_BP_QOutput">
	    <properties.wmqJms baseQueueManagerName="${QM_NAME}" baseQueueName="ANAGR_BP_QOutput"/>
	</jmsQueue>
	<jmsQueue id="jms/ANAGR_CONTRATTI_QOutput" jndiName="jms/ANAGR_CONTRATTI_QOutput">
	    <properties.wmqJms baseQueueManagerName="${QM_NAME}" baseQueueName="ANAGR_CONTRATTI_QOutput"/>
	</jmsQueue>
	<jmsQueue id="jms/ANAGR_CONTRATTI_QInput" jndiName="jms/ANAGR_CONTRATTI_QInput">
	    <properties.wmqJms baseQueueManagerName="${QM_NAME}" baseQueueName="ANAGR_CONTRATTI_QInput"/>
	</jmsQueue>
	<jmsQueue id="jms/ALTARES_STAMPINGS_QInput" jndiName="jms/ALTARES_STAMPINGS_QInput">
	    <properties.wmqJms baseQueueManagerName="${QM_NAME}" baseQueueName="ALTARES_STAMPINGS_QInput"/>
	</jmsQueue>
	<jmsQueue id="jms/WFM_CONF_QInput" jndiName="jms/WFM_CONF_QInput">
	    <properties.wmqJms baseQueueManagerName="${QM_NAME}" baseQueueName="WFM_CONF_QInput"/>
	</jmsQueue>
	<jmsQueue id="jms/WFM_CONF_QOutput" jndiName="jms/WFM_CONF_QOutput">
	    <properties.wmqJms baseQueueManagerName="${QM_NAME}" baseQueueName="WFM_CONF_QOutput"/>
	</jmsQueue>
	<jmsQueue id="jms/ANAGR_MEZZI_EXT_QInput" jndiName="jms/ANAGR_MEZZI_EXT_QInput">
	    <properties.wmqJms baseQueueManagerName="${QM_NAME}" baseQueueName="ANAGR_MEZZI_EXT_QInput"/>
	</jmsQueue>
	<jmsQueue id="jms/ANAGR_MEZZI_EXT_QOutput" jndiName="jms/ANAGR_MEZZI_EXT_QOutput">
	    <properties.wmqJms baseQueueManagerName="${QM_NAME}" baseQueueName="ANAGR_MEZZI_EXT_QOutput"/>
	</jmsQueue>
	<jmsQueue id="jms/ANAGR_CONTRATTI_PASSIVI_QInput" jndiName="jms/ANAGR_CONTRATTI_PASSIVI_QInput">
	    <properties.wmqJms baseQueueManagerName="${QM_NAME}" baseQueueName="ANAGR_CONTRATTI_PASSIVI_QInput"/>
	</jmsQueue>
	<jmsQueue id="jms/ANAGR_CONTRATTI_PASSIVI_QOutput" jndiName="jms/ANAGR_CONTRATTI_PASSIVI_QOutput">
	    <properties.wmqJms baseQueueManagerName="${QM_NAME}" baseQueueName="ANAGR_CONTRATTI_PASSIVI_QOutput"/>
	</jmsQueue>
	<jmsQueue id="jms/TCP_CONF_ISOLE_QOutput" jndiName="jms/TCP_CONF_ISOLE_QOutput">
	    <properties.wmqJms baseQueueManagerName="${QM_NAME}" baseQueueName="TCP_CONF_ISOLE_QOutput"/>
	</jmsQueue>
	<jmsQueue id="jms/GIS_ITINERARI_NOTE_QInput" jndiName="jms/GIS_ITINERARI_NOTE_QInput">
	    <properties.wmqJms baseQueueManagerName="${QM_NAME}" baseQueueName="GIS_ITINERARI_NOTE_QInput"/>
	</jmsQueue>
	<jmsQueue id="jms/CONF_ECOS_QInput" jndiName="jms/CONF_ECOS_QInput">
	    <properties.wmqJms baseQueueManagerName="${QM_NAME}" baseQueueName="CONF_ECOS_QInput"/>
	</jmsQueue>
	<jmsQueue id="jms/CONF_ECOS_QOutput" jndiName="jms/CONF_ECOS_QOutput">
	    <properties.wmqJms baseQueueManagerName="${QM_NAME}" baseQueueName="CONF_ECOS_QOutput"/>
	</jmsQueue>
	-->
	<!--  TOPICS -->
	<!--
	<jmsTopic id="jms/CONS_STATO" jndiName="jms/CONS_STATO">
	    <properties.wmqJms baseTopicName="CONS/STATO" brokerPubQueueManager="${QM_NAME}"/>
	</jmsTopic>
	<jmsTopic id="jms/CONS_ODL" jndiName="jms/CONS_ODL">
	    <properties.wmqJms baseTopicName="CONS/ODL" brokerPubQueueManager="${QM_NAME}"/>
	</jmsTopic>
	<jmsTopic id="jms/CONS_SEG" jndiName="jms/CONS_SEG">
	    <properties.wmqJms baseTopicName="CONS/SEG" brokerPubQueueManager="${QM_NAME}"/>
	</jmsTopic>
	<jmsTopic id="jms/CONS_TRACKING" jndiName="jms/CONS_TRACKING">
	    <properties.wmqJms baseTopicName="CONS/TRACKING" brokerPubQueueManager="${QM_NAME}"/>
	</jmsTopic>
	<jmsTopic id="jms/CONS_CHECKLIST" jndiName="jms/CONS_CHECKLIST">
	    <properties.wmqJms baseTopicName="CONS/CHECKLIST" brokerPubQueueManager="${QM_NAME}"/>
	</jmsTopic>
	<jmsTopic id="jms/CONS_PESATA" jndiName="jms/CONS_PESATA">
	    <properties.wmqJms baseTopicName="CONS/PESATA" brokerPubQueueManager="${QM_NAME}"/>
	</jmsTopic>
	<jmsTopic id="jms/CONS_ANOM" jndiName="jms/CONS_ANOM">
	    <properties.wmqJms baseTopicName="CONS/ANOM" brokerPubQueueManager="${QM_NAME}"/>
	</jmsTopic>
	<jmsTopic id="jms/CONS_CONFERIMENTI" jndiName="jms/CONS_CONFERIMENTI">
	    <properties.wmqJms baseTopicName="CONS/CONFERIMENTI" brokerPubQueueManager="${QM_NAME}"/>
	</jmsTopic>
	<jmsTopic id="jms/CONS_DOTAZIONI" jndiName="jms/CONS_DOTAZIONI">
	    <properties.wmqJms baseTopicName="CONS/DOTAZIONI" brokerPubQueueManager="${QM_NAME}"/>
	</jmsTopic>
	<jmsTopic id="jms/CONS_ECOSTATION" jndiName="jms/CONS_ECOSTATION">
	    <properties.wmqJms baseTopicName="CONS/ECOSTATION" brokerPubQueueManager="${QM_NAME}"/>
	</jmsTopic>
	-->

    <!--  definizione activation spec -->
    
    <!-- QUEUE AS-->
	<!--
    <jmsActivationSpec id="jms/ANAGR_SDC_Q_AS">
	    <properties.wmqJms channel="${QM_CHANNEL}" destinationRef="jms/ANAGR_SDC_QInput" destinationType="javax.jms.Queue" hostName="${QM_HOSTNAME}" maxPoolDepth="10" port="${QM_PORT}" queueManager="${QM_NAME}" transportType="CLIENT"/>
	</jmsActivationSpec>
	<jmsActivationSpec id="jms/ANAGR_UTENTI_Q_AS">
	    <properties.wmqJms channel="${QM_CHANNEL}" destinationRef="jms/ANAGR_UTENTI_QInput" destinationType="javax.jms.Queue" hostName="${QM_HOSTNAME}" maxPoolDepth="10" port="${QM_PORT}" queueManager="${QM_NAME}" transportType="CLIENT"/>
	</jmsActivationSpec>
	<jmsActivationSpec id="jms/ANAGR_CDL_Q_AS">
	    <properties.wmqJms channel="${QM_CHANNEL}" destinationRef="jms/ANAGR_CDL_QInput" destinationType="javax.jms.Queue" hostName="${QM_HOSTNAME}" maxPoolDepth="10" port="${QM_PORT}" queueManager="${QM_NAME}" transportType="CLIENT"/>
	</jmsActivationSpec>
	<jmsActivationSpec id="jms/WDO_Q_AS">
	    <properties.wmqJms channel="${QM_CHANNEL}" destinationRef="jms/WDO_QInput" destinationType="javax.jms.Queue" hostName="${QM_HOSTNAME}" maxPoolDepth="10" port="${QM_PORT}" queueManager="${QM_NAME}" transportType="CLIENT"/>
	</jmsActivationSpec>
	<jmsActivationSpec id="jms/ANAGR_MEZZI_Q_AS">
	    <properties.wmqJms channel="${QM_CHANNEL}" destinationRef="jms/ANAGR_MEZZI_QInput" destinationType="javax.jms.Queue" hostName="${QM_HOSTNAME}" maxPoolDepth="10" port="${QM_PORT}" queueManager="${QM_NAME}" transportType="CLIENT"/>
	</jmsActivationSpec>
	<jmsActivationSpec id="jms/NOT_Q_AS">
	    <properties.wmqJms channel="${QM_CHANNEL}" destinationRef="jms/NOT_QInput" destinationType="javax.jms.Queue" hostName="${QM_HOSTNAME}" maxPoolDepth="10" port="${QM_PORT}" queueManager="${QM_NAME}" transportType="CLIENT"/>
	</jmsActivationSpec>
	<jmsActivationSpec id="jms/CONS_WDO_Q_AS">
	    <properties.wmqJms channel="${QM_CHANNEL}" destinationRef="jms/CONS_WDO_QOutput" destinationType="javax.jms.Queue" hostName="${QM_HOSTNAME}" maxPoolDepth="10" port="${QM_PORT}" queueManager="${QM_NAME}" transportType="CLIENT"/>
	</jmsActivationSpec>
	<jmsActivationSpec id="jms/SEGNALAZIONI_Q_AS">
	    <properties.wmqJms channel="${QM_CHANNEL}" destinationRef="jms/SEGNALAZIONI_QOutput" destinationType="javax.jms.Queue" hostName="${QM_HOSTNAME}" maxPoolDepth="10" port="${QM_PORT}" queueManager="${QM_NAME}" transportType="CLIENT"/>
	</jmsActivationSpec>
	<jmsActivationSpec id="jms/ANAGR_CDR_Q_AS">
	    <properties.wmqJms channel="${QM_CHANNEL}" destinationRef="jms/ANAGR_CDR_QInput" destinationType="javax.jms.Queue" hostName="${QM_HOSTNAME}" maxPoolDepth="10" port="${QM_PORT}" queueManager="${QM_NAME}" transportType="CLIENT"/>
	</jmsActivationSpec>
	<jmsActivationSpec id="jms/ANAGR_WASTECONTAINER_Q_AS">
	    <properties.wmqJms channel="${QM_CHANNEL}" destinationRef="jms/ANAGR_WASTECONTAINER_QInput" destinationType="javax.jms.Queue" hostName="${QM_HOSTNAME}" maxPoolDepth="10" port="${QM_PORT}" queueManager="${QM_NAME}" transportType="CLIENT"/>
	</jmsActivationSpec>
	<jmsActivationSpec id="jms/ANAGR_PDR_Q_AS">
	    <properties.wmqJms channel="${QM_CHANNEL}" destinationRef="jms/ANAGR_PDR_QInput" destinationType="javax.jms.Queue" hostName="${QM_HOSTNAME}" maxPoolDepth="10" port="${QM_PORT}" queueManager="${QM_NAME}" transportType="CLIENT"/>
	</jmsActivationSpec>
	<jmsActivationSpec id="jms/CHECKLIST_Q_AS">
	    <properties.wmqJms channel="${QM_CHANNEL}" destinationRef="jms/CHECKLIST_QOutput" destinationType="javax.jms.Queue" hostName="${QM_HOSTNAME}" maxPoolDepth="10" port="${QM_PORT}" queueManager="${QM_NAME}" transportType="CLIENT"/>
	</jmsActivationSpec>
	<jmsActivationSpec id="jms/LOG_SAPMessages_Q_AS">
	    <properties.wmqJms channel="${QM_CHANNEL}" destinationRef="jms/LOG_SAPMessages" destinationType="javax.jms.Queue" hostName="${QM_HOSTNAME}" maxPoolDepth="10" port="${QM_PORT}" queueManager="${QM_NAME}" transportType="CLIENT"/>
	</jmsActivationSpec>
	<jmsActivationSpec id="jms/PERCORSI_EFFETTIVI_Q_AS">
	    <properties.wmqJms channel="${QM_CHANNEL}" destinationRef="jms/PERCORSI_EFFETTIVI_QOutput" destinationType="javax.jms.Queue" hostName="${QM_HOSTNAME}" maxPoolDepth="10" port="${QM_PORT}" queueManager="${QM_NAME}" transportType="CLIENT"/>
	</jmsActivationSpec>
	<jmsActivationSpec id="jms/TCP_ANAGR_SDC_Q_AS">
	    <properties.wmqJms channel="${QM_CHANNEL}" destinationRef="jms/TCP_ANAGR_SDC_QInput" destinationType="javax.jms.Queue" hostName="${QM_HOSTNAME}" maxPoolDepth="10" port="${QM_PORT}" queueManager="${QM_NAME}" transportType="CLIENT"/>
	</jmsActivationSpec>
	<jmsActivationSpec id="jms/TCP_BLACKLIST_Q_AS">
	    <properties.wmqJms channel="${QM_CHANNEL}" destinationRef="jms/TCP_BLACKLIST_QInput" destinationType="javax.jms.Queue" hostName="${QM_HOSTNAME}" maxPoolDepth="10" port="${QM_PORT}" queueManager="${QM_NAME}" transportType="CLIENT"/>
	</jmsActivationSpec>
	<jmsActivationSpec id="jms/TCP_CONF_Q_AS">
	    <properties.wmqJms channel="${QM_CHANNEL}" destinationRef="jms/TCP_CONF_QOutput" destinationType="javax.jms.Queue" hostName="${QM_HOSTNAME}" maxPoolDepth="10" port="${QM_PORT}" queueManager="${QM_NAME}" transportType="CLIENT"/>
	</jmsActivationSpec>
	<jmsActivationSpec id="jms/TCP_AGG_SDC_Q_AS">
	    <properties.wmqJms channel="${QM_CHANNEL}" destinationRef="jms/TCP_AGG_SDC_QOutput" destinationType="javax.jms.Queue" hostName="${QM_HOSTNAME}" maxPoolDepth="10" port="${QM_PORT}" queueManager="${QM_NAME}" transportType="CLIENT"/>
	</jmsActivationSpec>
	<jmsActivationSpec id="jms/TCP_BLACKLIST_INIBITA_Q_AS">
	    <properties.wmqJms channel="${QM_CHANNEL}" destinationRef="jms/TCP_BLACKLIST_INIBITA_QOutput" destinationType="javax.jms.Queue" hostName="${QM_HOSTNAME}" maxPoolDepth="10" port="${QM_PORT}" queueManager="${QM_NAME}" transportType="CLIENT"/>
	</jmsActivationSpec>
	<jmsActivationSpec id="jms/ANAGR_BP_Q_AS">
	    <properties.wmqJms channel="${QM_CHANNEL}" destinationRef="jms/ANAGR_BP_QInput" destinationType="javax.jms.Queue" hostName="${QM_HOSTNAME}" maxPoolDepth="10" port="${QM_PORT}" queueManager="${QM_NAME}" transportType="CLIENT"/>
	</jmsActivationSpec>
	<jmsActivationSpec id="jms/ANAGR_CONTRATTI_Q_AS">
	    <properties.wmqJms channel="${QM_CHANNEL}" destinationRef="jms/ANAGR_CONTRATTI_QInput" destinationType="javax.jms.Queue" hostName="${QM_HOSTNAME}" maxPoolDepth="10" port="${QM_PORT}" queueManager="${QM_NAME}" transportType="CLIENT"/>
	</jmsActivationSpec>
	<jmsActivationSpec id="jms/ALTARES_STAMPINGS_Q_AS">
	    <properties.wmqJms channel="${QM_CHANNEL}" destinationRef="jms/ALTARES_STAMPINGS_QInput" destinationType="javax.jms.Queue" hostName="${QM_HOSTNAME}" maxPoolDepth="10" port="${QM_PORT}" queueManager="${QM_NAME}" transportType="CLIENT"/>
	</jmsActivationSpec>
	<jmsActivationSpec id="jms/WFM_CONF_Q_AS">
	    <properties.wmqJms channel="${QM_CHANNEL}" destinationRef="jms/WFM_CONF_QInput" destinationType="javax.jms.Queue" hostName="${QM_HOSTNAME}" maxPoolDepth="10" port="${QM_PORT}" queueManager="${QM_NAME}" transportType="CLIENT"/>
	</jmsActivationSpec>
	<jmsActivationSpec id="jms/ANAGR_CONTRATTI_PASSIVI_Q_AS">
	    <properties.wmqJms channel="${QM_CHANNEL}" destinationRef="jms/ANAGR_CONTRATTI_PASSIVI_QInput" destinationType="javax.jms.Queue" hostName="${QM_HOSTNAME}" maxPoolDepth="10" port="${QM_PORT}" queueManager="${QM_NAME}" transportType="CLIENT"/>
	</jmsActivationSpec>
	<jmsActivationSpec id="jms/TCP_CONF_ISOLE_Q_AS">
	    <properties.wmqJms channel="${QM_CHANNEL}" destinationRef="jms/TCP_CONF_ISOLE_QOutput" destinationType="javax.jms.Queue" hostName="${QM_HOSTNAME}" maxPoolDepth="10" port="${QM_PORT}" queueManager="${QM_NAME}" transportType="CLIENT"/>
	</jmsActivationSpec>
	<jmsActivationSpec id="jms/GIS_ITINERARI_NOTE_Q_AS">
	    <properties.wmqJms channel="${QM_CHANNEL}" destinationRef="jms/GIS_ITINERARI_NOTE_QInput" destinationType="javax.jms.Queue" hostName="${QM_HOSTNAME}" maxPoolDepth="10" port="${QM_PORT}" queueManager="${QM_NAME}" transportType="CLIENT"/>
	</jmsActivationSpec>
	<jmsActivationSpec id="jms/CONF_ECOS_Q_AS">
	    <properties.wmqJms channel="${QM_CHANNEL}" destinationRef="jms/CONF_ECOS_QOutput" destinationType="javax.jms.Queue" hostName="${QM_HOSTNAME}" maxPoolDepth="10" port="${QM_PORT}" queueManager="${QM_NAME}" transportType="CLIENT"/>
	</jmsActivationSpec>
	-->
	<!-- TOPIC AS-->
	<!--
	<jmsActivationSpec id="jms/CONS_STATO_AS">
	    <properties.wmqJms channel="${QM_CHANNEL}"  destinationRef="jms/CONS_STATO" destinationType="javax.jms.Topic" hostName="${QM_HOSTNAME}" maxPoolDepth="10" port="${QM_PORT}" queueManager="${QM_NAME}" subscriptionDurability="Durable" subscriptionName="libertyServer" transportType="CLIENT"/>
	</jmsActivationSpec>
	<jmsActivationSpec id="jms/CONS_ODL_AS">
	    <properties.wmqJms channel="${QM_CHANNEL}" clientId="CONS_ODL-1" destinationRef="jms/CONS_ODL" destinationType="javax.jms.Topic" hostName="${QM_HOSTNAME}" maxPoolDepth="10" port="${QM_PORT}" queueManager="${QM_NAME}" subscriptionDurability="Durable" subscriptionName="libertyServer" transportType="CLIENT"/>
	</jmsActivationSpec>
	<jmsActivationSpec id="jms/CONS_SEG_AS">
	    <properties.wmqJms channel="${QM_CHANNEL}" clientId="CONS_SEG-1" destinationRef="jms/CONS_SEG" destinationType="javax.jms.Topic" hostName="${QM_HOSTNAME}" maxPoolDepth="10" port="${QM_PORT}" queueManager="${QM_NAME}" subscriptionDurability="Durable" subscriptionName="libertyServer" transportType="CLIENT"/>
	</jmsActivationSpec>
	<jmsActivationSpec id="jms/CONS_TRACKING_AS">
	    <properties.wmqJms channel="${QM_CHANNEL}" clientId="CONS_TRACKING-1" destinationRef="jms/CONS_TRACKING" destinationType="javax.jms.Topic" hostName="${QM_HOSTNAME}" maxPoolDepth="10" port="${QM_PORT}" queueManager="${QM_NAME}" subscriptionDurability="Durable" subscriptionName="libertyServer" transportType="CLIENT"/>
	</jmsActivationSpec>
	<jmsActivationSpec id="jms/CONS_CHECKLIST_AS">
	    <properties.wmqJms channel="${QM_CHANNEL}" clientId="CONS_CHECKLIST-1" destinationRef="jms/CONS_CHECKLIST" destinationType="javax.jms.Topic" hostName="${QM_HOSTNAME}" maxPoolDepth="10" port="${QM_PORT}" queueManager="${QM_NAME}" subscriptionDurability="Durable" subscriptionName="libertyServer" transportType="CLIENT"/>
	</jmsActivationSpec>
	<jmsActivationSpec id="jms/CONS_PESATA_AS">
	    <properties.wmqJms channel="${QM_CHANNEL}" clientId="CONS_PESATA_AS-1" destinationRef="jms/CONS_PESATA" destinationType="javax.jms.Topic" hostName="${QM_HOSTNAME}" maxPoolDepth="10" port="${QM_PORT}" queueManager="${QM_NAME}" subscriptionDurability="Durable" subscriptionName="libertyServer" transportType="CLIENT"/>
	</jmsActivationSpec>
	<jmsActivationSpec id="jms/CONS_ANOM_AS">
	    <properties.wmqJms channel="${QM_CHANNEL}" clientId="CONS_ANOM-1" destinationRef="jms/CONS_ANOM" destinationType="javax.jms.Topic" hostName="${QM_HOSTNAME}" maxPoolDepth="10" port="${QM_PORT}" queueManager="${QM_NAME}" subscriptionDurability="Durable" subscriptionName="libertyServer" transportType="CLIENT"/>
	</jmsActivationSpec>
	<jmsActivationSpec id="jms/CONS_CONFERIMENTI_AS">
	    <properties.wmqJms channel="${QM_CHANNEL}" clientId="CONS_CONFERIMENTI-1" destinationRef="jms/CONS_CONFERIMENTI" destinationType="javax.jms.Topic" hostName="${QM_HOSTNAME}" maxPoolDepth="10" port="${QM_PORT}" queueManager="${QM_NAME}" subscriptionDurability="Durable" subscriptionName="libertyServer" transportType="CLIENT"/>
	</jmsActivationSpec>
	<jmsActivationSpec id="jms/CONS_ECOSTATION_AS">
	    <properties.wmqJms channel="${QM_CHANNEL}" clientId="CONS_ECOSTATION-1" destinationRef="jms/CONS_ECOSTATION" destinationType="javax.jms.Topic" hostName="${QM_HOSTNAME}" maxPoolDepth="10" port="${QM_PORT}" queueManager="${QM_NAME}" subscriptionDurability="Durable" subscriptionName="libertyServer" transportType="CLIENT"/>
	</jmsActivationSpec>
	<jmsActivationSpec id="jms/CONS_DOTAZIONI_AS">
	    <properties.wmqJms channel="${QM_CHANNEL}" clientId="CONS_DOTAZIONI-1" destinationRef="jms/CONS_DOTAZIONI" destinationType="javax.jms.Topic" hostName="${QM_HOSTNAME}" maxPoolDepth="10" port="${QM_PORT}" queueManager="${QM_NAME}" subscriptionDurability="Durable" subscriptionName="libertyServer" transportType="CLIENT"/>
	</jmsActivationSpec>
     -->

	<!-- To access this server from a remote client add a host attribute to 
		the following element, e.g. host="*" -->
	<httpEndpoint host="*" httpPort="9080" httpsPort="9443" id="defaultHttpEndpoint"/>

	<!-- Automatically expand WAR files and EAR files -->
	<applicationManager autoExpand="true"/>
	
	<!-- Default SSL configuration enables trust for default certificates from the Java runtime --> 
    	<!-- <ssl id="defaultSSLConfig" trustDefaultCerts="true"/> --> 

	<applicationMonitor updateTrigger="mbean"/>
	
	<httpOptions persistTimeout="180s" readTimeout="180s" writeTimeout="180s"/>
	<tcpOptions inactivityTimeout="180s"/>

    
    
     <!-- EAR -->

<!--
    <enterpriseApplication id="WasteExtPortalEAR" location="WasteExtPortalEAR.ear" name="WasteExtPortalEAR">
    <classloader commonLibraryRef="OracleLib,WFMResource,properties"/>   
    </enterpriseApplication>
    
    

    <enterpriseApplication id="WastePortalEAR" location="WastePortalEAR.ear" name="WastePortalEAR">
    <classloader commonLibraryRef="OracleLib,WFMResource,properties"/> 
    </enterpriseApplication>
    
    
    <enterpriseApplication id="WasteIntegrationEAR" location="WasteIntegrationEAR.ear" name="WasteIntegrationEAR">
    <classloader commonLibraryRef="OracleLib,WFMResource,properties"/> 
    </enterpriseApplication>
     
	  -->
   

    <enterpriseApplication id="WasteDeviceEAR" location="${server.config.dir}/apps/WasteDeviceEAR.ear" name="WasteDeviceEAR">
    <classloader commonLibraryRef="postgresql-library,WFMResource,properties"/> 
    </enterpriseApplication>


</server>